llama_index/embeddings/adapter/__init__.py
llama_index/embeddings/adapter/base.py
llama_index/embeddings/adapter/utils.py
llama_index_embeddings_adapter-0.4.1.dist-info/METADATA
llama_index_embeddings_adapter-0.4.1.dist-info/WHEEL
llama_index_embeddings_adapter-0.4.1.dist-info/licenses/LICENSE
llama_index_embeddings_adapter-0.4.1.dist-info/RECORD
